LICENSE
MANIFEST.in
README.md
requirements.txt
setup.py
carto_report/__init__.py
carto_report/cli.py
carto_report/report.py
carto_report.egg-info/PKG-INFO
carto_report.egg-info/SOURCES.txt
carto_report.egg-info/dependency_links.txt
carto_report.egg-info/entry_points.txt
carto_report.egg-info/requires.txt
carto_report.egg-info/top_level.txt