Metadata-Version: 2.1
Name: carto-report
Version: 0.0.1
Summary: A module to export CARTO user database metrics
Home-page: https://github.com/CartoDB/labs-db-metrics
Author: Ramiro Aznar
Author-email: ramiroaznar@carto.com
License: BSD
Keywords: carto cli cartodb api reporting postgres
Platform: UNKNOWN
Classifier: License :: OSI Approved :: BSD License
Classifier: Programming Language :: Python :: 3
Classifier: Programming Language :: Python :: 3.7
